quadratic_function_solver_kemulk/__init__.py
quadratic_function_solver_kemulk/quadratic_function_solver.py
quadratic_function_solver_kemulk-0.0.3.dist-info/LICENSE
quadratic_function_solver_kemulk-0.0.3.dist-info/METADATA
quadratic_function_solver_kemulk-0.0.3.dist-info/WHEEL
quadratic_function_solver_kemulk-0.0.3.dist-info/top_level.txt
quadratic_function_solver_kemulk-0.0.3.dist-info/RECORD
